MAAP/AudioCutter.py
MAAP/AudioFeature.py
MAAP/AudioFeatureExtractor.py
MAAP/AudioReader.py
MAAP/AudioReceiver.py
MAAP/AudioSignal.py
MAAP/AudioWriter.py
MAAP/__init__.py
MAAP/utils/AudioFeature2Tensor.py
MAAP/utils/__init__.py
MAAP/utils/concat_audio_signal.py
MAAP-0.2.1.dist-info/LICENSE.txt
MAAP-0.2.1.dist-info/METADATA
MAAP-0.2.1.dist-info/WHEEL
MAAP-0.2.1.dist-info/top_level.txt
MAAP-0.2.1.dist-info/RECORD
