Metadata-Version: 2.1
Name: MAAP
Version: 0.2.1
Summary: UNKNOWN
Home-page: https://github.com/pficardoso/MAAP
Author: Pedro Cardoso
Author-email: pedro.cardoso.code@gmail.com
License: MIT
Project-URL: Source, https://github.com/pficardoso/MAAP
Platform: any
Classifier: Development Status :: 3 - Alpha
Classifier: Programming Language :: Python
License-File: LICENSE.txt
Requires-Dist: librosa (<1.0.0,>=0.8.1)
Requires-Dist: numpy (==1.20.3)
Requires-Dist: SoundFile (<1.0.0,>=0.10.3)
Requires-Dist: sounddevice (<1.0.0,>=0.4.1)
Requires-Dist: matplotlib (<4.0.0,>=3.3.4)
Requires-Dist: importlib-metadata ; python_version < "3.8"
Provides-Extra: testing
Requires-Dist: setuptools ; extra == 'testing'
Requires-Dist: pytest ; extra == 'testing'
Requires-Dist: pytest-cov ; extra == 'testing'
